{"cameraMode":{"drawMode":0,"name":"Shaded","section":"Shading Mode"},"sceneLighting":true,"audioPlay":false,"sceneViewState":{"m_AlwaysRefresh":false,"showFog":true,"showSkybox":true,"showFlares":true,"showImageEffects":true,"showParticleSystems":true,"showVisualEffectGraphs":true,"m_FxEnabled":true},"in2DMode":false,"pivot":{"x":-3.673863649368286,"y":13.403667449951172,"z":-3.9919185638427736},"rotation":{"x":0.3361251652240753,"y":-0.1291225701570511,"z":0.04658982902765274,"w":0.9317709803581238},"size":2.6802966594696047,"orthographic":false}